{
  "@context": "https://api.wellcomecollection.org/catalogue/v0/context.json",
  "id": "watu9tbc",
  "type": "Work",
  "workType" : {
      "id" : "image" ,
      "label" : "Image" ,
  } ,
  "identifiers": 
    [
      {
        "value": "V0006724",
		"type": "Identifier" ,
        "identifierScheme": "miro-image-number"
      },
      {
        "value": "ICV No 6939",
		"type": "Identifier" ,
        "identifierScheme": "wellcome-library-videodisk-number"
      },
      {
        "value": "b11579328",
		"type": "Identifier" ,		
        "identifierScheme": "sierra-system-number"
      }
    ],
  "title": "A lecture on pneumatics at the Royal Institution, London. Co",
  "description": "A lecture on pneumatics at the Royal Institution, London. Coloured etching by J. Gillray, 1802.",
  "lettering": "Scientific researches! -New discoveries in pneumaticks! -or- an experimental lecture on the powers of air.- Js. Gillray inv. & fect.",
  "creators": 
    [
		
      {
		"label": "James Gillray"
      }
    ],
  "publishers": 
    [
      {
        "label": "H. Humphrey,"
      }
    ],
  "placeOfPublication": 
     [
       {
        "label": "[London] (St. James's Street)",
        "type": "Place"
      }
    ],
  "createdDate": 
    {
      "label": "1802",
      "type": "Period"
    },
  "publicationDate": 
    {
      "label": "May 23 1802",
      "type": "Period"
    },
  "genres":
  [	   
	  {
           "label": "Caricatures",
		   "type": "Concept",
		   "identifiers": [
		   		{
		   			"type": "Identifier",
					"identifierScheme": "lctgm" ,
					"value": "Caricatures"
		   		}
		   ] 	   	
	   } , 
	   {
	       "label": "Etching and water colour" ,
		   "type": "Concept" 	   	
	   } 
   ],
  "physicalDescription": "etching, with watercolour"  , 
  "subjects": 
    [
      {
        "label": "Thomas Young [1773  - 1829 ]",
		"type": "Concept"
      },
      {
        "label": "Count von Rumford Sir Benjamin Thompson [1753  - 1814 ]",
		"type": "Concept"
      },
      {
        "label": "Sir Humphry Davy [1778  - 1829 ]",
		"type": "Concept"
      },
      {
        "label": "Sir John Coxe Hippisley [1748  - 1825 ]",
		"type": "Concept"
      },
      {
        "label": "Royal Institution of Great Britain [ - ]",
		"type": "Concept"
      }
    ],
  "items":
    [
      {
       "id": "b28gh7z4n",
       "type": "Item",
		"identifiers": 
        [
          {
            "value": "V0006724",
			"type": "Identifier" ,
            "identifierScheme": "miro-image-number" ,
          }
        ],
		"locations" :
         [
			 {
		     "type": "PhysicalLocation" ,
			 "locationType": {
				 "id" : "sicon" ,
				 "label" : "Closed Store Iconographic" ,
				 "url" : "http://catalogue.wellcomelibrary.org/screens/loc_closed_online_icon.html" , 
				 "type" : "LocationType"
			     } ,
			 "identifiers": {
				 "type" : "Identifier" ,
				 "identifierScheme" : "icon-shelfmark" ,
				 "value" : "1L9N"
			 } ,
			 "accessStatus":{
				 "id" : "open" ,
				 "type" : "AccessStatus"
			     } ,
			 "accessProcess" : {
				 "id" : "online-access" ,
				 "label" : "Online access" ,
				 "type" : "AccessProcess" 
				 } ,
			 } ,
			 {
		     "id" : "https://dlcs.io/iiif-img/wellcome/1/b28gh7z4n" ,
			 "type": "DigitalLocation" ,
			 "locationType": "iiif-image" ,
			 "label" : "IIIF Image API" ,
			 "url" : "http://wellcomelibrary.org/what-we-do/digitisation/" , 
		 	 "license" : {
		 		"type" : "License" ,
		 	    "label" : "CC-BY-4.0" ,
		 		"description" : "Copyrighted work available under Creative Commons Attribution only licence CC BY 4.0" ,
		 	    "url" : "http://creativecommons.org/licenses/by/4.0/" ,	
		 		} ,
			 } ,
		 ] 	
       }
    ]
}
